napackage/__init__.py
napackage/nodemanager.py
hwnapack-0.0.1.dist-info/LICENSE
hwnapack-0.0.1.dist-info/METADATA
hwnapack-0.0.1.dist-info/WHEEL
hwnapack-0.0.1.dist-info/top_level.txt
hwnapack-0.0.1.dist-info/RECORD
