Metadata-Version: 2.1
Name: hwnapack
Version: 0.0.1
Summary: A hw nuisance package
Home-page: https://github.com/ashokdhudla/NuisanceAlarms
Author: Ashok
Author-email: ashok@example.com
License: UNKNOWN
Project-URL: Bug Tracker, https://github.com/pypa/sampleproject/issues
Platform: UNKNOWN
Classifier: Programming Language :: Python :: 3
Classifier: License :: OSI Approved :: MIT License
Classifier: Operating System :: OS Independent
Requires-Python: >=3.6
License-File: LICENSE
